hello_hxhkim-0.3.0.dist-info/METADATA
hello_hxhkim-0.3.0.dist-info/WHEEL
hello_hxhkim/__init__.py
hello_hxhkim/demo.py
hello_hxhkim/who.py
hello_hxhkim-0.3.0.dist-info/RECORD
