Metadata-Version: 2.1
Name: hello-hxhkim
Version: 0.3.0
Summary: The first deploying python program.
Author-Email: hxhkim <hxhkim1998@gmail.com>
License: MIT
Requires-Python: >=3.8
